{
    "option": {
        "gameName": "古剑奇谭网络版",
        "defaultFont": "true",
        "sharedMemory": "true",
        "writeCopy": "true",
        "rtServer": "ture",
        "dockSystemVersion": "win7",
        "wineVersion":"wine5.6-dev"
    },
    "env": {
        "env1": "value1",
        "env2": "value2",
        "env3": "value3"
    },
    "dll": [
        "vc++2013",
        "vc++2015"
    ],
    "dxvk": {
        "dxvkState": "true",
        "dxvkVersion": "dxvk-1.7",
        "dxvkHUD": "true"
    },
    "reg": {
        "key": "value",
        "key2": "value"
    },
    "Args": "value"
}